icinga2telegram.py
icinga2telegram-0.2.2.dist-info/LICENSE
icinga2telegram-0.2.2.dist-info/METADATA
icinga2telegram-0.2.2.dist-info/WHEEL
icinga2telegram-0.2.2.dist-info/entry_points.txt
icinga2telegram-0.2.2.dist-info/top_level.txt
icinga2telegram-0.2.2.dist-info/RECORD
