Metadata-Version: 2.1
Name: icinga2telegram
Version: 0.2.2
Summary: Send your Icinga2 alerts to Telegram
Home-page: https://github.com/ekeih/icinga2telegram
Author: Max Rosin
Author-email: git@hackrid.de
License: LICENSE
Platform: UNKNOWN
Requires-Dist: Click
Requires-Dist: emoji
Requires-Dist: Jinja2
Requires-Dist: python-telegram-bot
